tenops/__init__.py
tenops/grid.py
tenops/manage.py
tenops/reduce.py
tenops/special.py
tenops/trig.py
tenops/utils.py
tenops-0.2.0.dist-info/METADATA
tenops-0.2.0.dist-info/WHEEL
tenops-0.2.0.dist-info/RECORD
