Metadata-Version: 2.1
Name: tenops
Version: 0.2.0
Summary: Python package for creating a common interface for using numpy, pytorch, etc.
Home-page: https://github.com/bbergerud/tenops
License: MIT
Author: Brandon Bergerud
Author-email: brandon.bergerud@gmail.com
Requires-Python: >=3.9,<4.0
Classifier: License :: OSI Approved :: MIT License
Classifier: Programming Language :: Python :: 3
Classifier: Programming Language :: Python :: 3.9
Classifier: Programming Language :: Python :: 3.10
Classifier: Programming Language :: Python :: 3.11
Classifier: Programming Language :: Python :: 3.12
Project-URL: Repository, https://github.com/bbergerud/tenops
